{"5":{"5":{"method":"path, local","obj":240.97756187424326},"12":{"method":"path, local","obj":240.97756187424326},"8":{"method":"path, local","obj":240.97756187424326},"1":{"method":"path, local","obj":240.97756187424326},"6":{"method":"path, local","obj":240.97756187424326},"11":{"method":"path, local","obj":240.97756187424326},"9":{"method":"path, local","obj":240.97756187424326},"14":{"method":"path, local","obj":240.97756187424326},"3":{"method":"path, local","obj":240.97756187424326},"7":{"method":"path, local","obj":240.97756187424326},"4":{"method":"path, local","obj":240.97756187424326},"13":{"method":"path, local","obj":240.97756187424326},"15":{"method":"local","obj":240.97756187424326},"2":{"method":"path, local","obj":240.97756187424326},"10":{"method":"path, local","obj":240.97756187424326}},"16":{"5":{"method":"remove","obj":240.97756187424326},"12":{"method":"remove","obj":240.97756187424326},"8":{"method":"remove","obj":240.97756187424326},"1":{"method":"remove","obj":240.97756187424326},"6":{"method":"remove","obj":240.97756187424326},"11":{"method":"remove","obj":240.97756187424326},"9":{"method":"remove","obj":240.97756187424326},"14":{"method":"remove","obj":240.97756187424326},"3":{"method":"remove","obj":240.97756187424326},"7":{"method":"remove","obj":240.97756187424326},"4":{"method":"remove","obj":240.97756187424326},"13":{"method":"remove","obj":240.97756187424326},"15":{"method":"remove","obj":240.97756187424326},"2":{"method":"remove","obj":240.97756187424326},"10":{"method":"remove","obj":240.97756187424326}},"12":{"5":{"method":"path, local","obj":240.9775618742433},"12":{"method":"path, local","obj":240.9775618742433},"8":{"method":"path, local","obj":240.9775618742433},"1":{"method":"path, local","obj":240.9775618742433},"6":{"method":"path, local","obj":240.9775618742433},"11":{"method":"path, local","obj":240.9775618742433},"9":{"method":"path, local","obj":240.9775618742433},"14":{"method":"path, local","obj":240.9775618742433},"3":{"method":"path, local","obj":240.9775618742433},"7":{"method":"path, local","obj":240.9775618742433},"4":{"method":"path, local","obj":240.9775618742433},"13":{"method":"path, local","obj":240.9775618742433},"15":{"method":"local","obj":240.97756187424326},"2":{"method":"path, local","obj":240.9775618742433},"10":{"method":"path, local","obj":240.9775618742433}},"8":{"5":{"method":"path, local","obj":240.97756187424326},"12":{"method":"path, local","obj":240.97756187424326},"8":{"method":"path, local","obj":240.97756187424326},"1":{"method":"local","obj":240.97756187424326},"6":{"method":"path, local","obj":240.97756187424326},"11":{"method":"path, local","obj":240.97756187424326},"9":{"method":"path, local","obj":240.97756187424326},"14":{"method":"path, local","obj":240.97756187424326},"3":{"method":"path, local","obj":240.97756187424326},"7":{"method":"path, local","obj":240.97756187424326},"4":{"method":"path, local","obj":240.97756187424326},"13":{"method":"path, local","obj":240.97756187424326},"15":{"method":"path, local","obj":240.97756187424326},"2":{"method":"path, local","obj":240.97756187424326},"10":{"method":"path, local","obj":240.97756187424326}},"17":{"5":{"method":"path, local","obj":515.5382777811562},"12":{"method":"path, local","obj":312.9736075061108},"8":{"method":"path, local","obj":503.4479987528205},"1":{"method":"path, local","obj":521.256234824899},"6":{"method":"path, local","obj":497.8195999097455},"11":{"method":"path, local","obj":324.93299831527156},"9":{"method":"path, local","obj":463.55513069833063},"14":{"method":"path, local","obj":273.37828321220167},"3":{"method":"path, local","obj":514.1874071258571},"7":{"method":"path, local","obj":318.1418557857794},"4":{"method":"path, local","obj":289.70372222785886},"13":{"method":"path, local","obj":523.2576894997144},"15":{"method":"local","obj":240.97756187424326},"2":{"method":"path, local","obj":305.7910518093607},"10":{"method":"path, local","obj":465.6117287573027}},"1":{"5":{"method":"path, local","obj":609.8073454145159},"12":{"method":"path, local","obj":410.05940808419604},"8":{"method":"path, local","obj":649.7412977922405},"1":{"method":"path, local","obj":672.775424728676},"6":{"method":"path, local","obj":705.1989559312964},"11":{"method":"path, local","obj":328.11598167151436},"9":{"method":"path, local","obj":576.2835110664768},"14":{"method":"path, local","obj":542.8309385354529},"3":{"method":"path, local","obj":695.059172300032},"7":{"method":"path, local","obj":829.1257681669221},"4":{"method":"path, local","obj":623.4048299214469},"13":{"method":"path, local","obj":365.2341517740797},"15":{"method":"local","obj":260.25969963934364},"2":{"method":"path, local","obj":667.7514027087941},"10":{"method":"path, local","obj":569.7314270094331}},"6":{"5":{"method":"path, local","obj":240.97756187424326},"12":{"method":"path, local","obj":240.97756187424326},"8":{"method":"path, local","obj":240.97756187424326},"1":{"method":"local","obj":240.97756187424326},"6":{"method":"path, local","obj":240.97756187424326},"11":{"method":"path, local","obj":240.97756187424326},"9":{"method":"path, local","obj":240.97756187424326},"14":{"method":"path, local","obj":240.97756187424326},"3":{"method":"path, local","obj":240.97756187424326},"7":{"method":"path, local","obj":240.97756187424326},"4":{"method":"path, local","obj":240.97756187424326},"13":{"method":"path, local","obj":240.97756187424326},"15":{"method":"path, local","obj":240.97756187424326},"2":{"method":"path, local","obj":240.97756187424326},"10":{"method":"path, local","obj":240.97756187424326}},"11":{"5":{"method":"path, local","obj":512.8217941168516},"12":{"method":"path, local","obj":328.2435301864945},"8":{"method":"path, local","obj":550.7538135908437},"1":{"method":"path, local","obj":276.3868878106027},"6":{"method":"path, local","obj":546.7086015700552},"11":{"method":"path, local","obj":278.9816551608919},"9":{"method":"path, local","obj":459.3614616748966},"14":{"method":"path, local","obj":333.4357386590085},"3":{"method":"path, local","obj":499.44370525207825},"7":{"method":"path, local","obj":343.95998013972354},"4":{"method":"path, local","obj":319.1498112856872},"13":{"method":"path, local","obj":303.8028718364623},"15":{"method":"local","obj":240.97756187424326},"2":{"method":"path, local","obj":367.70719269016115},"10":{"method":"path, local","obj":477.9871612451307}},"9":{"5":{"method":"random","obj":581.5314290959946},"12":{"method":"random","obj":770.5435964517775},"8":{"method":"random","obj":622.4736102111493},"1":{"method":"random","obj":645.6649341232493},"6":{"method":"random","obj":639.0155387022188},"11":{"method":"random","obj":727.930150406847},"9":{"method":"random","obj":522.6731386849922},"14":{"method":"random","obj":619.9258931155855},"3":{"method":"random","obj":653.6248275473991},"7":{"method":"random","obj":832.1960729034506},"4":{"method":"random","obj":645.7266125409164},"13":{"method":"random","obj":721.6574681377444},"15":{"method":"random","obj":240.97756187424326},"2":{"method":"random","obj":704.4349880212012},"10":{"method":"random","obj":505.39546988943295}},"14":{"5":{"method":"path, local","obj":240.97756187424326},"12":{"method":"path, local","obj":240.97756187424326},"8":{"method":"path, local","obj":240.97756187424326},"1":{"method":"local","obj":240.97756187424326},"6":{"method":"path, local","obj":240.97756187424326},"11":{"method":"path, local","obj":240.97756187424326},"9":{"method":"path, local","obj":240.97756187424326},"14":{"method":"path, local","obj":240.97756187424326},"3":{"method":"path, local","obj":240.97756187424326},"7":{"method":"path, local","obj":240.97756187424326},"4":{"method":"path, local","obj":240.97756187424326},"13":{"method":"path, local","obj":240.97756187424326},"15":{"method":"path, local","obj":240.97756187424326},"2":{"method":"path, local","obj":240.97756187424326},"10":{"method":"path, local","obj":240.97756187424326}},"3":{"5":{"method":"path, local","obj":428.92480169789707},"12":{"method":"path, local","obj":307.42543756038305},"8":{"method":"path, local","obj":271.4588545423909},"1":{"method":"path, local","obj":313.5579303666776},"6":{"method":"path, local","obj":302.8001921712865},"11":{"method":"path, local","obj":283.8654637752506},"9":{"method":"path, local","obj":366.6140251793426},"14":{"method":"path, local","obj":275.01882832752335},"3":{"method":"path, local","obj":275.0188283275233},"7":{"method":"path, local","obj":283.86546377525053},"4":{"method":"path, local","obj":417.1514659632366},"13":{"method":"path, local","obj":283.8654637752506},"15":{"method":"local","obj":240.97756187424326},"2":{"method":"path, local","obj":308.95038557267804},"10":{"method":"path, local","obj":326.7625354962332}},"7":{"5":{"method":"path, local","obj":240.9775618742433},"12":{"method":"path, local","obj":240.9775618742433},"8":{"method":"path, local","obj":240.9775618742433},"1":{"method":"local","obj":240.97756187424326},"6":{"method":"path, local","obj":240.9775618742433},"11":{"method":"path, local","obj":240.9775618742433},"9":{"method":"path, local","obj":240.9775618742433},"14":{"method":"path, local","obj":240.9775618742433},"3":{"method":"path, local","obj":240.9775618742433},"7":{"method":"path, local","obj":240.9775618742433},"4":{"method":"path, local","obj":240.9775618742433},"13":{"method":"path, local","obj":240.9775618742433},"15":{"method":"path, local","obj":240.9775618742433},"2":{"method":"path, local","obj":240.9775618742433},"10":{"method":"path, local","obj":240.9775618742433}},"4":{"5":{"method":"path, local","obj":297.4224187422654},"12":{"method":"path, local","obj":275.8974707299703},"8":{"method":"path, local","obj":240.9775618742433},"1":{"method":"path, local","obj":244.53753565937575},"6":{"method":"path, local","obj":260.31465981009353},"11":{"method":"path, local","obj":264.53753565937575},"9":{"method":"path, local","obj":272.7212690429532},"14":{"method":"path, local","obj":240.9775618742433},"3":{"method":"path, local","obj":240.9775618742433},"7":{"method":"path, local","obj":264.53753565937575},"4":{"method":"path, local","obj":272.7212690429532},"13":{"method":"path, local","obj":272.3374969448378},"15":{"method":"local","obj":240.97756187424326},"2":{"method":"path, local","obj":272.3374969448378},"10":{"method":"path, local","obj":319.70553112256147}},"13":{"5":{"method":"path, local","obj":240.97756187424326},"12":{"method":"path, local","obj":240.97756187424326},"8":{"method":"path, local","obj":240.97756187424326},"1":{"method":"path, local","obj":240.97756187424326},"6":{"method":"path, local","obj":240.97756187424326},"11":{"method":"path, local","obj":240.97756187424326},"9":{"method":"path, local","obj":240.97756187424326},"14":{"method":"path, local","obj":240.97756187424326},"3":{"method":"path, local","obj":240.97756187424326},"7":{"method":"path, local","obj":240.97756187424326},"4":{"method":"path, local","obj":240.97756187424326},"13":{"method":"path, local","obj":240.97756187424326},"15":{"method":"local","obj":240.97756187424326},"2":{"method":"path, local","obj":240.97756187424326},"10":{"method":"path, local","obj":240.97756187424326}},"15":{"5":{"method":"random","obj":581.5314290959946},"12":{"method":"random","obj":770.5435964517775},"8":{"method":"random","obj":622.4736102111493},"1":{"method":"random","obj":645.6649341232493},"6":{"method":"random","obj":639.0155387022188},"11":{"method":"random","obj":727.930150406847},"9":{"method":"random","obj":522.6731386849922},"14":{"method":"random","obj":619.9258931155855},"3":{"method":"random","obj":653.6248275473991},"7":{"method":"random","obj":832.1960729034506},"4":{"method":"random","obj":645.7266125409164},"13":{"method":"random","obj":721.6574681377444},"15":{"method":"random","obj":240.97756187424326},"2":{"method":"random","obj":704.4349880212012},"10":{"method":"random","obj":505.39546988943295}},"2":{"5":{"method":"path, local","obj":436.26450609202004},"12":{"method":"path, local","obj":315.5633805931861},"8":{"method":"path, local","obj":317.08832860548114},"1":{"method":"path, local","obj":320.26003351060837},"6":{"method":"path, local","obj":292.00340680805357},"11":{"method":"path, local","obj":292.00340680805357},"9":{"method":"path, local","obj":381.8173845552627},"14":{"method":"path, local","obj":283.8196734244761},"3":{"method":"path, local","obj":288.5163263418984},"7":{"method":"path, local","obj":292.00340680805357},"4":{"method":"path, local","obj":424.58625087739324},"13":{"method":"path, local","obj":292.00340680805357},"15":{"method":"local","obj":252.1217566065406},"2":{"method":"path, local","obj":317.0883286054811},"10":{"method":"path, local","obj":315.563380593186}},"10":{"5":{"method":"remove","obj":240.97756187424326},"12":{"method":"remove","obj":240.97756187424326},"8":{"method":"remove","obj":240.97756187424326},"1":{"method":"remove","obj":240.97756187424326},"6":{"method":"remove","obj":240.97756187424326},"11":{"method":"remove","obj":240.97756187424326},"9":{"method":"remove","obj":240.97756187424326},"14":{"method":"remove","obj":240.97756187424326},"3":{"method":"remove","obj":240.97756187424326},"7":{"method":"remove","obj":240.97756187424326},"4":{"method":"remove","obj":240.97756187424326},"13":{"method":"remove","obj":240.97756187424326},"15":{"method":"remove","obj":240.97756187424326},"2":{"method":"remove","obj":240.97756187424326},"10":{"method":"remove","obj":240.97756187424326}}}