{"5":{"5":{"method":"path, local","obj":1439.1073272322208},"12":{"method":"path, local","obj":1402.5107519302226},"8":{"method":"path, local","obj":1319.2887365817674},"1":{"method":"path, local","obj":1286.9096760157536},"6":{"method":"path, local","obj":1287.472554345752},"11":{"method":"path, local","obj":1483.511681502262},"9":{"method":"path, local","obj":1343.5840906251633},"14":{"method":"path, local","obj":1465.7022594795856},"3":{"method":"path, local","obj":1379.6084061773875},"7":{"method":"local","obj":1217.9457230534415},"4":{"method":"path, local","obj":1230.765865863252},"13":{"method":"path, local","obj":1381.8206180889208},"15":{"method":"path, local","obj":1255.241909400057},"2":{"method":"path, local","obj":1220.5749003896985},"10":{"method":"path, local","obj":1243.6271224054406}},"16":{"5":{"method":"path, local","obj":968.4843222766253},"12":{"method":"path, local","obj":985.7270378791734},"8":{"method":"path, local","obj":943.9300341389026},"1":{"method":"path, local","obj":925.9640974720577},"6":{"method":"path, local","obj":927.4616479360554},"11":{"method":"path, local","obj":925.9640974720578},"9":{"method":"local","obj":905.0910508444613},"14":{"method":"path, local","obj":959.1336323427026},"3":{"method":"path, local","obj":925.9640974720578},"7":{"method":"path, local","obj":925.9640974720578},"4":{"method":"path, local","obj":953.0195205302061},"13":{"method":"path, local","obj":925.9640974720578},"15":{"method":"path, local","obj":1012.1577897448715},"2":{"method":"path, local","obj":925.9640974720578},"10":{"method":"path, local","obj":925.9640974720578}},"20":{"5":{"method":"path, local","obj":932.0210185078561},"12":{"method":"path, local","obj":970.3693605675102},"8":{"method":"path, local","obj":928.1620078947683},"1":{"method":"path, local","obj":928.1620078947683},"6":{"method":"path, local","obj":933.6298911849478},"11":{"method":"path, local","obj":929.522074580158},"9":{"method":"local","obj":905.0910508444613},"14":{"method":"path, local","obj":959.1336323427028},"3":{"method":"path, local","obj":928.1620078947683},"7":{"method":"path, local","obj":928.1620078947683},"4":{"method":"path, local","obj":958.1999857916794},"13":{"method":"path, local","obj":925.9640974720579},"15":{"method":"path, local","obj":968.7259236343413},"2":{"method":"path, local","obj":928.1620078947683},"10":{"method":"path, local","obj":928.1620078947683}},"35":{"5":{"method":"path, local","obj":905.7097167606248},"12":{"method":"path, local","obj":905.1716468625623},"8":{"method":"path, local","obj":925.964097472058},"1":{"method":"path, local","obj":927.0266802428994},"6":{"method":"local","obj":903.265557526859},"11":{"method":"path, local","obj":925.964097472058},"9":{"method":"path, local","obj":905.0910508444613},"14":{"method":"path, local","obj":925.964097472058},"3":{"method":"path, local","obj":927.0266802428994},"7":{"method":"path, local","obj":927.0266802428994},"4":{"method":"path, local","obj":925.964097472058},"13":{"method":"path, local","obj":925.964097472058},"15":{"method":"path, local","obj":925.964097472058},"2":{"method":"path, local","obj":927.0266802428994},"10":{"method":"path, local","obj":925.964097472058}},"12":{"5":{"method":"path, local","obj":1008.0201015130685},"12":{"method":"path, local","obj":1056.1874109337057},"8":{"method":"path, local","obj":977.9307270741253},"1":{"method":"path, local","obj":1072.4999680316187},"6":{"method":"path, local","obj":981.1328257616001},"11":{"method":"local","obj":928.9243776519116},"9":{"method":"path, local","obj":1194.9165411864933},"14":{"method":"path, local","obj":1148.4585927329106},"3":{"method":"path, local","obj":963.1337714050198},"7":{"method":"path, local","obj":1105.6807997775059},"4":{"method":"path, local","obj":961.8543519229872},"13":{"method":"path, local","obj":1014.5583843832571},"15":{"method":"path, local","obj":1049.8116193134592},"2":{"method":"path, local","obj":998.930103916606},"10":{"method":"path, local","obj":1236.5198827587299}},"24":{"5":{"method":"path, local","obj":905.7097167606247},"12":{"method":"path, local","obj":905.171646862562},"8":{"method":"path, local","obj":925.9640974720578},"1":{"method":"path, local","obj":925.9640974720578},"6":{"method":"local","obj":903.265557526859},"11":{"method":"path, local","obj":925.9640974720578},"9":{"method":"path, local","obj":905.0910508444613},"14":{"method":"path, local","obj":959.1336323427026},"3":{"method":"path, local","obj":927.0266802428994},"7":{"method":"path, local","obj":925.9640974720578},"4":{"method":"path, local","obj":925.9640974720578},"13":{"method":"path, local","obj":927.0266802428994},"15":{"method":"path, local","obj":957.9916024748795},"2":{"method":"path, local","obj":927.0266802428994},"10":{"method":"path, local","obj":925.9640974720578}},"28":{"5":{"method":"path, local","obj":905.7097167606247},"12":{"method":"path, local","obj":905.171646862562},"8":{"method":"path, local","obj":925.9640974720579},"1":{"method":"path, local","obj":925.9640974720579},"6":{"method":"local","obj":903.265557526859},"11":{"method":"path, local","obj":925.9640974720579},"9":{"method":"path, local","obj":905.0910508444612},"14":{"method":"path, local","obj":959.1336323427026},"3":{"method":"path, local","obj":925.9640974720579},"7":{"method":"path, local","obj":925.9640974720579},"4":{"method":"path, local","obj":925.9640974720579},"13":{"method":"path, local","obj":925.9640974720579},"15":{"method":"path, local","obj":957.9916024748796},"2":{"method":"path, local","obj":925.9640974720579},"10":{"method":"path, local","obj":925.9640974720579}},"8":{"5":{"method":"path, local","obj":1502.4655511818219},"12":{"method":"path, local","obj":1423.2783084269524},"8":{"method":"path, local","obj":1123.8438489279356},"1":{"method":"path, local","obj":1151.982964008272},"6":{"method":"path, local","obj":1373.6105607108336},"11":{"method":"local","obj":1019.1019248755858},"9":{"method":"path, local","obj":1395.111182178761},"14":{"method":"path, local","obj":1233.4194642211032},"3":{"method":"path, local","obj":1085.418614106107},"7":{"method":"path, local","obj":1150.1322770402533},"4":{"method":"path, local","obj":1131.3449152963076},"13":{"method":"path, local","obj":1418.2515785157116},"15":{"method":"path, local","obj":1255.4534786187812},"2":{"method":"path, local","obj":1132.200292171992},"10":{"method":"path, local","obj":1298.1409834648068}},"17":{"5":{"method":"path, local","obj":968.4843222766256},"12":{"method":"path, local","obj":985.7270378791736},"8":{"method":"path, local","obj":943.9300341389026},"1":{"method":"path, local","obj":925.964097472058},"6":{"method":"path, local","obj":927.4616479360557},"11":{"method":"path, local","obj":925.964097472058},"9":{"method":"local","obj":905.0910508444613},"14":{"method":"path, local","obj":959.1336323427029},"3":{"method":"path, local","obj":925.964097472058},"7":{"method":"path, local","obj":925.964097472058},"4":{"method":"path, local","obj":953.0195205302064},"13":{"method":"path, local","obj":925.964097472058},"15":{"method":"path, local","obj":1012.1577897448715},"2":{"method":"path, local","obj":925.964097472058},"10":{"method":"path, local","obj":925.964097472058}},"30":{"5":{"method":"path, local","obj":905.7097167606246},"12":{"method":"path, local","obj":905.171646862562},"8":{"method":"path, local","obj":925.9640974720579},"1":{"method":"path, local","obj":925.9640974720579},"6":{"method":"local","obj":903.265557526859},"11":{"method":"path, local","obj":925.9640974720579},"9":{"method":"path, local","obj":905.0910508444613},"14":{"method":"path, local","obj":959.1336323427026},"3":{"method":"path, local","obj":925.9640974720579},"7":{"method":"path, local","obj":925.9640974720579},"4":{"method":"path, local","obj":925.9640974720579},"13":{"method":"path, local","obj":925.9640974720579},"15":{"method":"path, local","obj":957.9916024748796},"2":{"method":"path, local","obj":925.9640974720579},"10":{"method":"path, local","obj":925.9640974720579}},"1":{"5":{"method":"path, local","obj":3817.7879945408777},"12":{"method":"path, local","obj":3252.959119424184},"8":{"method":"path, local","obj":3314.410345156676},"1":{"method":"path, local","obj":3627.1955226715045},"6":{"method":"path, local","obj":3302.253733341371},"11":{"method":"path, local","obj":3708.66823839848},"9":{"method":"path, local","obj":3249.586194197893},"14":{"method":"path, local","obj":3944.2630479564996},"3":{"method":"path, local","obj":3696.3639398747773},"7":{"method":"local","obj":1613.1579490069803},"4":{"method":"path, local","obj":3602.8898164997618},"13":{"method":"path, local","obj":1690.7260600045133},"15":{"method":"path, local","obj":3575.855364751265},"2":{"method":"path, local","obj":3776.4510541416885},"10":{"method":"path, local","obj":3255.5001972903588}},"19":{"5":{"method":"path, local","obj":932.0210185078561},"12":{"method":"path, local","obj":972.3701652784391},"8":{"method":"path, local","obj":984.0722843926612},"1":{"method":"path, local","obj":965.3901305276936},"6":{"method":"path, local","obj":975.1384844097518},"11":{"method":"path, local","obj":965.3901305276937},"9":{"method":"local","obj":905.0910508444613},"14":{"method":"path, local","obj":998.5596653983384},"3":{"method":"path, local","obj":965.3901305276936},"7":{"method":"path, local","obj":965.3901305276937},"4":{"method":"path, local","obj":993.1617707839649},"13":{"method":"path, local","obj":965.3901305276936},"15":{"method":"path, local","obj":1048.039244054935},"2":{"method":"path, local","obj":965.3901305276936},"10":{"method":"path, local","obj":965.3901305276936}},"22":{"5":{"method":"path, local","obj":932.0210185078561},"12":{"method":"path, local","obj":906.5768328018567},"8":{"method":"path, local","obj":925.9640974720579},"1":{"method":"path, local","obj":925.9640974720579},"6":{"method":"local","obj":903.265557526859},"11":{"method":"path, local","obj":925.9640974720579},"9":{"method":"path, local","obj":905.0910508444614},"14":{"method":"path, local","obj":959.1336323427026},"3":{"method":"path, local","obj":925.9640974720579},"7":{"method":"path, local","obj":925.964097472058},"4":{"method":"path, local","obj":925.9640974720579},"13":{"method":"path, local","obj":925.9640974720579},"15":{"method":"path, local","obj":967.933182445417},"2":{"method":"path, local","obj":925.9640974720579},"10":{"method":"path, local","obj":925.9640974720579}},"23":{"5":{"method":"path, local","obj":960.9278054274167},"12":{"method":"path, local","obj":905.171646862562},"8":{"method":"path, local","obj":928.8859091075108},"1":{"method":"path, local","obj":928.8859091075108},"6":{"method":"local","obj":903.265557526859},"11":{"method":"path, local","obj":928.8859091075108},"9":{"method":"path, local","obj":905.0910508444612},"14":{"method":"path, local","obj":962.0554439781555},"3":{"method":"path, local","obj":928.8859091075108},"7":{"method":"path, local","obj":928.8859091075109},"4":{"method":"path, local","obj":928.8859091075108},"13":{"method":"path, local","obj":928.8859091075108},"15":{"method":"path, local","obj":961.0818875956676},"2":{"method":"path, local","obj":928.8859091075108},"10":{"method":"path, local","obj":928.8859091075108}},"6":{"5":{"method":"path, local","obj":1500.8901644236525},"12":{"method":"path, local","obj":1447.3840738541478},"8":{"method":"path, local","obj":1345.163604383631},"1":{"method":"path, local","obj":1355.5120245616336},"6":{"method":"path, local","obj":1346.7071593658484},"11":{"method":"path, local","obj":1491.6066053186312},"9":{"method":"path, local","obj":1386.2590092902535},"14":{"method":"path, local","obj":1490.7571749128865},"3":{"method":"path, local","obj":1419.2341536433155},"7":{"method":"local","obj":1197.0582182821815},"4":{"method":"path, local","obj":1282.3767361333987},"13":{"method":"path, local","obj":1453.377275691892},"15":{"method":"path, local","obj":1302.8053084948772},"2":{"method":"path, local","obj":1271.5454293156886},"10":{"method":"path, local","obj":1303.2284437090166}},"32":{"5":{"method":"path, local","obj":905.7097167606246},"12":{"method":"path, local","obj":905.1716468625622},"8":{"method":"path, local","obj":928.8859091075108},"1":{"method":"path, local","obj":928.8859091075108},"6":{"method":"local","obj":903.265557526859},"11":{"method":"path, local","obj":928.8859091075108},"9":{"method":"path, local","obj":905.0910508444613},"14":{"method":"path, local","obj":928.8859091075108},"3":{"method":"path, local","obj":928.8859091075108},"7":{"method":"path, local","obj":928.8859091075108},"4":{"method":"path, local","obj":928.8859091075108},"13":{"method":"path, local","obj":928.8859091075108},"15":{"method":"path, local","obj":928.8859091075108},"2":{"method":"path, local","obj":928.8859091075108},"10":{"method":"path, local","obj":928.8859091075108}},"11":{"5":{"method":"path, local","obj":1063.9801255110347},"12":{"method":"path, local","obj":1055.4423857887061},"8":{"method":"path, local","obj":1009.8576726200822},"1":{"method":"path, local","obj":1000.231754667968},"6":{"method":"path, local","obj":1010.167728064944},"11":{"method":"local","obj":928.9243776519116},"9":{"method":"path, local","obj":1123.3360283241868},"14":{"method":"path, local","obj":1078.2091219366075},"3":{"method":"path, local","obj":1009.7229505889327},"7":{"method":"path, local","obj":1078.8962914871713},"4":{"method":"path, local","obj":1018.0227860455584},"13":{"method":"path, local","obj":1044.452404072742},"15":{"method":"path, local","obj":1154.6200300465266},"2":{"method":"path, local","obj":929.5123975763298},"10":{"method":"path, local","obj":1165.8486656565897}},"36":{"5":{"method":"path, local","obj":946.6229207731288},"12":{"method":"path, local","obj":942.571582409954},"8":{"method":"path, local","obj":971.2827254149041},"1":{"method":"path, local","obj":972.3453081857455},"6":{"method":"local","obj":903.265557526859},"11":{"method":"path, local","obj":971.2827254149041},"9":{"method":"path, local","obj":946.7335249169138},"14":{"method":"path, local","obj":971.2827254149041},"3":{"method":"path, local","obj":972.3453081857455},"7":{"method":"path, local","obj":972.3453081857455},"4":{"method":"path, local","obj":971.2827254149041},"13":{"method":"path, local","obj":971.2827254149041},"15":{"method":"path, local","obj":971.2827254149041},"2":{"method":"path, local","obj":972.3453081857455},"10":{"method":"path, local","obj":971.2827254149041}},"9":{"5":{"method":"path, local","obj":1579.148904033259},"12":{"method":"path, local","obj":1500.953546259566},"8":{"method":"path, local","obj":1202.3120830737757},"1":{"method":"path, local","obj":1229.2021182084777},"6":{"method":"path, local","obj":1451.4582970539489},"11":{"method":"local","obj":931.6325348754323},"9":{"method":"path, local","obj":1472.7864200113747},"14":{"method":"path, local","obj":1309.3853373363288},"3":{"method":"path, local","obj":1161.0668204136064},"7":{"method":"path, local","obj":1220.4035800779598},"4":{"method":"path, local","obj":1076.4020065788607},"13":{"method":"path, local","obj":1496.0993148588268},"15":{"method":"path, local","obj":1333.3755440911134},"2":{"method":"path, local","obj":1210.3045115036628},"10":{"method":"path, local","obj":1376.6092176106474}},"31":{"5":{"method":"path, local","obj":905.7097167606246},"12":{"method":"path, local","obj":905.171646862562},"8":{"method":"path, local","obj":925.9640974720579},"1":{"method":"path, local","obj":925.9640974720579},"6":{"method":"local","obj":903.265557526859},"11":{"method":"path, local","obj":925.9640974720579},"9":{"method":"path, local","obj":905.0910508444612},"14":{"method":"path, local","obj":925.9640974720579},"3":{"method":"path, local","obj":925.9640974720579},"7":{"method":"path, local","obj":925.9640974720579},"4":{"method":"path, local","obj":925.9640974720579},"13":{"method":"path, local","obj":925.9640974720579},"15":{"method":"path, local","obj":925.9640974720579},"2":{"method":"path, local","obj":925.9640974720579},"10":{"method":"path, local","obj":925.9640974720579}},"14":{"5":{"method":"path, local","obj":976.7807907078721},"12":{"method":"path, local","obj":985.7270378791735},"8":{"method":"path, local","obj":943.9300341389024},"1":{"method":"path, local","obj":925.9640974720577},"6":{"method":"path, local","obj":979.0241013871331},"11":{"method":"path, local","obj":925.9640974720578},"9":{"method":"path, local","obj":947.0141357844908},"14":{"method":"path, local","obj":959.1336323427025},"3":{"method":"path, local","obj":925.9640974720577},"7":{"method":"path, local","obj":925.9640974720578},"4":{"method":"path, local","obj":953.0195205302061},"13":{"method":"path, local","obj":925.9640974720577},"15":{"method":"path, local","obj":1012.1577897448715},"2":{"method":"local","obj":925.9640974720581},"10":{"method":"path, local","obj":925.9640974720577}},"3":{"5":{"method":"path, local","obj":3423.6317283764547},"12":{"method":"path, local","obj":2927.608948912388},"8":{"method":"path, local","obj":3025.0163834301748},"1":{"method":"path, local","obj":3332.032949714804},"6":{"method":"path, local","obj":1557.8395761598},"11":{"method":"path, local","obj":3348.659764923446},"9":{"method":"path, local","obj":1433.5092956380429},"14":{"method":"path, local","obj":3670.329837500454},"3":{"method":"path, local","obj":3374.1519804754994},"7":{"method":"local","obj":1278.0631646498052},"4":{"method":"path, local","obj":1334.7273172194366},"13":{"method":"path, local","obj":1727.6478500676385},"15":{"method":"path, local","obj":1342.331160778919},"2":{"method":"path, local","obj":3362.4797128173905},"10":{"method":"path, local","obj":3013.7053526073632}},"29":{"5":{"method":"path, local","obj":905.7097167606245},"12":{"method":"path, local","obj":905.171646862562},"8":{"method":"path, local","obj":925.9640974720579},"1":{"method":"path, local","obj":925.9640974720579},"6":{"method":"local","obj":903.265557526859},"11":{"method":"path, local","obj":925.9640974720579},"9":{"method":"path, local","obj":905.0910508444612},"14":{"method":"path, local","obj":959.1336323427025},"3":{"method":"path, local","obj":925.9640974720579},"7":{"method":"path, local","obj":925.9640974720579},"4":{"method":"path, local","obj":925.9640974720579},"13":{"method":"path, local","obj":925.9640974720579},"15":{"method":"path, local","obj":957.9916024748795},"2":{"method":"path, local","obj":925.9640974720579},"10":{"method":"path, local","obj":925.9640974720579}},"7":{"5":{"method":"path, local","obj":1495.1779541732292},"12":{"method":"path, local","obj":1414.5369462854205},"8":{"method":"path, local","obj":1344.5128453859718},"1":{"method":"path, local","obj":1357.80891568409},"6":{"method":"path, local","obj":1352.9190433327467},"11":{"method":"path, local","obj":1092.5696682386001},"9":{"method":"path, local","obj":1392.5639460061536},"14":{"method":"path, local","obj":1222.2323934166998},"3":{"method":"path, local","obj":1418.6149826054996},"7":{"method":"local","obj":1195.99563551134},"4":{"method":"path, local","obj":1115.6307829430862},"13":{"method":"path, local","obj":1454.949146538654},"15":{"method":"path, local","obj":1270.6857584481727},"2":{"method":"path, local","obj":1118.5707155711834},"10":{"method":"path, local","obj":1310.7978180973203}},"25":{"5":{"method":"path, local","obj":905.7097167606246},"12":{"method":"path, local","obj":905.1716468625619},"8":{"method":"path, local","obj":925.9640974720577},"1":{"method":"path, local","obj":925.9640974720577},"6":{"method":"local","obj":903.265557526859},"11":{"method":"path, local","obj":925.9640974720578},"9":{"method":"path, local","obj":905.0910508444612},"14":{"method":"path, local","obj":959.1336323427025},"3":{"method":"path, local","obj":925.9640974720577},"7":{"method":"path, local","obj":925.9640974720577},"4":{"method":"path, local","obj":925.9640974720577},"13":{"method":"path, local","obj":925.9640974720577},"15":{"method":"path, local","obj":957.9916024748794},"2":{"method":"path, local","obj":925.9640974720577},"10":{"method":"path, local","obj":925.9640974720577}},"33":{"5":{"method":"path, local","obj":905.7097167606246},"12":{"method":"path, local","obj":905.1716468625622},"8":{"method":"path, local","obj":927.0266802428993},"1":{"method":"path, local","obj":925.9640974720578},"6":{"method":"local","obj":903.265557526859},"11":{"method":"path, local","obj":925.9640974720578},"9":{"method":"path, local","obj":905.0910508444613},"14":{"method":"path, local","obj":925.9640974720578},"3":{"method":"path, local","obj":925.9640974720578},"7":{"method":"path, local","obj":927.0266802428993},"4":{"method":"path, local","obj":927.0266802428993},"13":{"method":"path, local","obj":925.9640974720578},"15":{"method":"path, local","obj":927.0266802428993},"2":{"method":"path, local","obj":927.0266802428993},"10":{"method":"path, local","obj":925.9640974720578}},"34":{"5":{"method":"path, local","obj":905.7097167606246},"12":{"method":"path, local","obj":905.1716468625622},"8":{"method":"path, local","obj":928.8859091075108},"1":{"method":"path, local","obj":928.8859091075108},"6":{"method":"local","obj":903.265557526859},"11":{"method":"path, local","obj":928.8859091075108},"9":{"method":"path, local","obj":905.0910508444613},"14":{"method":"path, local","obj":928.8859091075108},"3":{"method":"path, local","obj":928.8859091075108},"7":{"method":"path, local","obj":928.8859091075108},"4":{"method":"path, local","obj":928.8859091075108},"13":{"method":"path, local","obj":928.8859091075108},"15":{"method":"path, local","obj":928.8859091075108},"2":{"method":"path, local","obj":928.8859091075108},"10":{"method":"path, local","obj":928.8859091075108}},"4":{"5":{"method":"path, local","obj":3401.0270583307515},"12":{"method":"path, local","obj":2991.330495906812},"8":{"method":"path, local","obj":3006.2821045268884},"1":{"method":"path, local","obj":3394.8576103578225},"6":{"method":"path, local","obj":1621.9786447459257},"11":{"method":"path, local","obj":3365.51557831911},"9":{"method":"path, local","obj":1491.7002220824452},"14":{"method":"path, local","obj":3622.7055002586835},"3":{"method":"path, local","obj":3375.133901563744},"7":{"method":"local","obj":1257.88134270155},"4":{"method":"path, local","obj":1397.1332993082578},"13":{"method":"path, local","obj":1791.3693970620627},"15":{"method":"path, local","obj":1404.2493429280898},"2":{"method":"path, local","obj":3386.507538684066},"10":{"method":"path, local","obj":3077.5293561885237}},"13":{"5":{"method":"path, local","obj":988.680875384602},"12":{"method":"path, local","obj":994.5618692719544},"8":{"method":"path, local","obj":966.095559199499},"1":{"method":"path, local","obj":1003.0286940536963},"6":{"method":"path, local","obj":991.0261079125661},"11":{"method":"local","obj":928.9243776519116},"9":{"method":"path, local","obj":947.5476506034503},"14":{"method":"path, local","obj":983.146436433302},"3":{"method":"path, local","obj":925.9640974720581},"7":{"method":"path, local","obj":935.5916700537631},"4":{"method":"path, local","obj":953.0195205302065},"13":{"method":"path, local","obj":980.0174940049586},"15":{"method":"path, local","obj":1012.1577897448714},"2":{"method":"path, local","obj":925.9640974720581},"10":{"method":"path, local","obj":969.1712440220068}},"15":{"5":{"method":"path, local","obj":968.4843222766256},"12":{"method":"path, local","obj":985.7270378791736},"8":{"method":"path, local","obj":943.9300341389026},"1":{"method":"local","obj":925.9640974720577},"6":{"method":"path, local","obj":953.5504041740244},"11":{"method":"path, local","obj":925.964097472058},"9":{"method":"path, local","obj":910.3261557159731},"14":{"method":"path, local","obj":959.1336323427029},"3":{"method":"path, local","obj":925.964097472058},"7":{"method":"path, local","obj":925.964097472058},"4":{"method":"path, local","obj":953.0195205302064},"13":{"method":"path, local","obj":925.964097472058},"15":{"method":"path, local","obj":1012.1577897448715},"2":{"method":"path, local","obj":925.9640974720578},"10":{"method":"path, local","obj":925.964097472058}},"2":{"5":{"method":"path, local","obj":3621.261211288664},"12":{"method":"path, local","obj":3102.699443227736},"8":{"method":"path, local","obj":3151.85144958635},"1":{"method":"path, local","obj":3564.9511807844647},"6":{"method":"path, local","obj":1439.6157489737163},"11":{"method":"path, local","obj":3476.7452393041362},"9":{"method":"path, local","obj":3094.385765280651},"14":{"method":"path, local","obj":3811.913350697595},"3":{"method":"path, local","obj":3606.101644019258},"7":{"method":"local","obj":1340.2117591870197},"4":{"method":"path, local","obj":3459.1206268386613},"13":{"method":"path, local","obj":1750.2662668299054},"15":{"method":"path, local","obj":3286.6031668610167},"2":{"method":"path, local","obj":3614.4708960297826},"10":{"method":"path, local","obj":3160.361885332487}},"10":{"5":{"method":"path, local","obj":1183.0556059360547},"12":{"method":"path, local","obj":1150.2567549844234},"8":{"method":"path, local","obj":1082.490388189666},"1":{"method":"path, local","obj":1064.5143355845653},"6":{"method":"path, local","obj":1101.9848627137173},"11":{"method":"local","obj":928.9243776519116},"9":{"method":"path, local","obj":1141.708516032565},"14":{"method":"path, local","obj":1045.538220281413},"3":{"method":"path, local","obj":1017.4628752781997},"7":{"method":"path, local","obj":1077.4972915279097},"4":{"method":"path, local","obj":1037.7093161924245},"13":{"method":"path, local","obj":1259.329878553777},"15":{"method":"path, local","obj":1147.6389354901528},"2":{"method":"path, local","obj":1002.7245492426291},"10":{"method":"path, local","obj":1156.5803719368773}},"18":{"5":{"method":"path, local","obj":968.4843222766254},"12":{"method":"path, local","obj":985.7270378791735},"8":{"method":"path, local","obj":943.9300341389024},"1":{"method":"path, local","obj":925.9640974720577},"6":{"method":"path, local","obj":927.4616479360556},"11":{"method":"path, local","obj":925.9640974720579},"9":{"method":"local","obj":905.0910508444613},"14":{"method":"path, local","obj":959.1336323427025},"3":{"method":"path, local","obj":925.9640974720579},"7":{"method":"path, local","obj":925.9640974720579},"4":{"method":"path, local","obj":953.0195205302063},"13":{"method":"path, local","obj":925.9640974720579},"15":{"method":"path, local","obj":1012.7769859156898},"2":{"method":"path, local","obj":925.9640974720579},"10":{"method":"path, local","obj":925.9640974720579}},"21":{"5":{"method":"path, local","obj":932.021018507856},"12":{"method":"path, local","obj":942.2455690617693},"8":{"method":"path, local","obj":925.9640974720577},"1":{"method":"path, local","obj":925.9640974720577},"6":{"method":"path, local","obj":903.265557526859},"11":{"method":"path, local","obj":925.9640974720578},"9":{"method":"local","obj":905.0910508444613},"14":{"method":"path, local","obj":959.1336323427025},"3":{"method":"path, local","obj":925.9640974720577},"7":{"method":"path, local","obj":925.9640974720577},"4":{"method":"path, local","obj":930.6382237388794},"13":{"method":"path, local","obj":925.9640974720577},"15":{"method":"path, local","obj":967.9331824454167},"2":{"method":"path, local","obj":925.9640974720577},"10":{"method":"path, local","obj":925.9640974720577}},"26":{"5":{"method":"path, local","obj":905.7097167606247},"12":{"method":"path, local","obj":905.1716468625622},"8":{"method":"path, local","obj":925.9640974720579},"1":{"method":"path, local","obj":925.9640974720579},"6":{"method":"local","obj":903.265557526859},"11":{"method":"path, local","obj":925.9640974720578},"9":{"method":"path, local","obj":905.0910508444612},"14":{"method":"path, local","obj":959.1336323427028},"3":{"method":"path, local","obj":925.9640974720579},"7":{"method":"path, local","obj":925.9640974720578},"4":{"method":"path, local","obj":925.9640974720579},"13":{"method":"path, local","obj":925.9640974720579},"15":{"method":"path, local","obj":957.9916024748796},"2":{"method":"path, local","obj":925.9640974720579},"10":{"method":"path, local","obj":925.9640974720579}},"27":{"5":{"method":"path, local","obj":905.7097167606246},"12":{"method":"path, local","obj":905.1716468625622},"8":{"method":"path, local","obj":925.9640974720579},"1":{"method":"path, local","obj":925.9640974720579},"6":{"method":"local","obj":903.265557526859},"11":{"method":"path, local","obj":925.9640974720579},"9":{"method":"path, local","obj":905.0910508444613},"14":{"method":"path, local","obj":959.1336323427026},"3":{"method":"path, local","obj":925.9640974720579},"7":{"method":"path, local","obj":925.9640974720578},"4":{"method":"path, local","obj":925.9640974720579},"13":{"method":"path, local","obj":925.9640974720579},"15":{"method":"path, local","obj":957.9916024748795},"2":{"method":"path, local","obj":925.9640974720579},"10":{"method":"path, local","obj":925.9640974720579}}}