{"5":{"5":{"method":"path, local","obj":260.07293571571967},"12":{"method":"path, local","obj":263.03380231306505},"8":{"method":"path, local","obj":247.89721490121187},"1":{"method":"path, local","obj":515.6016972689082},"6":{"method":"path, local","obj":317.38036900095386},"11":{"method":"path, local","obj":568.2799773539426},"9":{"method":"path, local","obj":308.4069557801937},"14":{"method":"path, local","obj":307.40160810984486},"3":{"method":"local","obj":244.5715262985879},"7":{"method":"path, local","obj":684.0124634873151},"4":{"method":"path, local","obj":373.18441118972964},"13":{"method":"path, local","obj":298.1705514895438},"15":{"method":"path, local","obj":323.3170296271267},"2":{"method":"path, local","obj":515.541252556595},"10":{"method":"path, local","obj":261.79089617921943}},"8":{"5":{"method":"path, local","obj":527.8629090433543},"12":{"method":"path, local","obj":530.8237756406996},"8":{"method":"path, local","obj":247.89721490121187},"1":{"method":"path, local","obj":783.3916705965428},"6":{"method":"path, local","obj":317.38036900095386},"11":{"method":"path, local","obj":836.0699506815772},"9":{"method":"path, local","obj":308.4069557801937},"14":{"method":"path, local","obj":307.40160810984486},"3":{"method":"local","obj":244.5715262985879},"7":{"method":"path, local","obj":951.8024368149497},"4":{"method":"path, local","obj":432.6726421232628},"13":{"method":"path, local","obj":298.1705514895438},"15":{"method":"path, local","obj":323.3170296271267},"2":{"method":"path, local","obj":783.3312258842298},"10":{"method":"path, local","obj":529.580869506854}},"1":{"5":{"method":"path, local","obj":356.45559414718633},"12":{"method":"path, local","obj":282.3484558435508},"8":{"method":"path, local","obj":320.0932567947067},"1":{"method":"path, local","obj":281.58991671621544},"6":{"method":"path, local","obj":319.6960809353033},"11":{"method":"path, local","obj":303.5512296308295},"9":{"method":"path, local","obj":334.9775441805345},"14":{"method":"path, local","obj":307.40160810984486},"3":{"method":"local","obj":244.5715262985879},"7":{"method":"path, local","obj":335.29006599167656},"4":{"method":"path, local","obj":336.1251066303681},"13":{"method":"path, local","obj":363.93636081021},"15":{"method":"path, local","obj":380.6516688811634},"2":{"method":"path, local","obj":319.5750320489491},"10":{"method":"path, local","obj":277.44731558544373}},"6":{"5":{"method":"path, local","obj":364.22380691277044},"12":{"method":"path, local","obj":367.1846735101158},"8":{"method":"path, local","obj":247.89721490121187},"1":{"method":"path, local","obj":619.7525684659589},"6":{"method":"path, local","obj":317.38036900095386},"11":{"method":"path, local","obj":672.4308485509931},"9":{"method":"path, local","obj":308.4069557801937},"14":{"method":"path, local","obj":307.40160810984486},"3":{"method":"local","obj":244.5715262985879},"7":{"method":"path, local","obj":788.1633346843659},"4":{"method":"path, local","obj":373.18441118972964},"13":{"method":"path, local","obj":298.1705514895438},"15":{"method":"path, local","obj":323.3170296271267},"2":{"method":"path, local","obj":619.6921237536459},"10":{"method":"path, local","obj":365.94176737627015}},"11":{"5":{"method":"path, local","obj":795.6528823709888},"12":{"method":"path, local","obj":798.6137489683341},"8":{"method":"path, local","obj":247.89721490121187},"1":{"method":"path, local","obj":1051.1816439241773},"6":{"method":"path, local","obj":317.38036900095386},"11":{"method":"path, local","obj":1103.8599240092117},"9":{"method":"path, local","obj":308.4069557801937},"14":{"method":"path, local","obj":307.40160810984486},"3":{"method":"local","obj":244.5715262985879},"7":{"method":"path, local","obj":1219.5924101425844},"4":{"method":"path, local","obj":700.4626154508974},"13":{"method":"path, local","obj":298.1705514895438},"15":{"method":"path, local","obj":323.3170296271267},"2":{"method":"path, local","obj":1051.1211992118642},"10":{"method":"path, local","obj":797.3708428344885}},"9":{"5":{"method":"path, local","obj":632.0137802404048},"12":{"method":"path, local","obj":634.9746468377501},"8":{"method":"path, local","obj":247.89721490121187},"1":{"method":"path, local","obj":887.5425417935934},"6":{"method":"path, local","obj":317.38036900095386},"11":{"method":"path, local","obj":940.2208218786278},"9":{"method":"path, local","obj":308.4069557801937},"14":{"method":"path, local","obj":307.40160810984486},"3":{"method":"local","obj":244.5715262985879},"7":{"method":"path, local","obj":1055.9533080120004},"4":{"method":"path, local","obj":536.8235133203135},"13":{"method":"path, local","obj":298.1705514895438},"15":{"method":"path, local","obj":323.3170296271267},"2":{"method":"path, local","obj":887.4820970812804},"10":{"method":"path, local","obj":633.7317407039046}},"3":{"5":{"method":"path, local","obj":288.6328177721186},"12":{"method":"path, local","obj":282.3484558435508},"8":{"method":"path, local","obj":247.89721490121187},"1":{"method":"path, local","obj":351.96259513832433},"6":{"method":"path, local","obj":317.38036900095386},"11":{"method":"path, local","obj":404.64087522335865},"9":{"method":"path, local","obj":321.295951716762},"14":{"method":"path, local","obj":307.40160810984486},"3":{"method":"local","obj":244.5715262985879},"7":{"method":"path, local","obj":520.3733613567313},"4":{"method":"path, local","obj":313.69618025619667},"13":{"method":"path, local","obj":298.1705514895438},"15":{"method":"path, local","obj":323.3170296271267},"2":{"method":"path, local","obj":351.9021504260112},"10":{"method":"path, local","obj":262.9763341810857}},"7":{"5":{"method":"path, local","obj":468.37467810982116},"12":{"method":"path, local","obj":471.3355447071665},"8":{"method":"path, local","obj":247.89721490121187},"1":{"method":"path, local","obj":723.9034396630096},"6":{"method":"path, local","obj":317.38036900095386},"11":{"method":"path, local","obj":776.581719748044},"9":{"method":"path, local","obj":308.4069557801937},"14":{"method":"path, local","obj":307.40160810984486},"3":{"method":"local","obj":244.5715262985879},"7":{"method":"path, local","obj":892.3142058814166},"4":{"method":"path, local","obj":373.18441118972964},"13":{"method":"path, local","obj":298.1705514895438},"15":{"method":"path, local","obj":323.3170296271267},"2":{"method":"path, local","obj":723.8429949506966},"10":{"method":"path, local","obj":470.0926385733209}},"4":{"5":{"method":"path, local","obj":288.6328177721186},"12":{"method":"path, local","obj":282.3484558435508},"8":{"method":"path, local","obj":247.89721490121187},"1":{"method":"path, local","obj":456.11346633537505},"6":{"method":"path, local","obj":317.38036900095386},"11":{"method":"path, local","obj":508.7917464204094},"9":{"method":"path, local","obj":321.295951716762},"14":{"method":"path, local","obj":307.40160810984486},"3":{"method":"local","obj":244.5715262985879},"7":{"method":"path, local","obj":624.524232553782},"4":{"method":"path, local","obj":313.69618025619667},"13":{"method":"path, local","obj":298.1705514895438},"15":{"method":"path, local","obj":323.3170296271267},"2":{"method":"path, local","obj":456.05302162306197},"10":{"method":"path, local","obj":262.9763341810857}},"2":{"5":{"method":"path, local","obj":297.0079740423277},"12":{"method":"path, local","obj":282.3484558435508},"8":{"method":"path, local","obj":281.87378676545745},"1":{"method":"path, local","obj":247.81172394127358},"6":{"method":"path, local","obj":317.38036900095386},"11":{"method":"path, local","obj":300.490004026308},"9":{"method":"path, local","obj":321.295951716762},"14":{"method":"path, local","obj":307.40160810984486},"3":{"method":"local","obj":244.5715262985879},"7":{"method":"path, local","obj":416.22249015968055},"4":{"method":"path, local","obj":323.68379463889374},"13":{"method":"path, local","obj":313.7258053588021},"15":{"method":"path, local","obj":323.3170296271267},"2":{"method":"path, local","obj":247.75127922896053},"10":{"method":"path, local","obj":264.41031258129584}},"10":{"5":{"method":"path, local","obj":691.5020111739382},"12":{"method":"path, local","obj":694.4628777712835},"8":{"method":"path, local","obj":247.89721490121187},"1":{"method":"path, local","obj":947.0307727271266},"6":{"method":"path, local","obj":317.38036900095386},"11":{"method":"path, local","obj":999.709052812161},"9":{"method":"path, local","obj":308.4069557801937},"14":{"method":"path, local","obj":307.40160810984486},"3":{"method":"local","obj":244.5715262985879},"7":{"method":"path, local","obj":1115.4415389455332},"4":{"method":"path, local","obj":596.3117442538467},"13":{"method":"path, local","obj":298.1705514895438},"15":{"method":"path, local","obj":323.3170296271267},"2":{"method":"path, local","obj":946.9703280148136},"10":{"method":"path, local","obj":693.2199716374378}}}